wxtrio/__init__.py
wxtrio/core.py
wxtrio-0.2.2.dist-info/LICENSE
wxtrio-0.2.2.dist-info/METADATA
wxtrio-0.2.2.dist-info/WHEEL
wxtrio-0.2.2.dist-info/top_level.txt
wxtrio-0.2.2.dist-info/RECORD
