Metadata-Version: 2.1
Name: wxtrio
Version: 0.2.2
Summary: Async wxPtyon with trio.
Author: lojack5
License: BSD 3-Clause
Project-URL: homepage, https://github.com/lojack5/wxtrio
Keywords: wxPython,trio,async,GUI
Classifier: Intended Audience :: Developers
Classifier: License :: OSI Approved :: BSD License
Classifier: Programming Language :: Python :: 3 :: Only
Classifier: Programming Language :: Python :: 3.11
Classifier: Framework :: Trio
Requires-Python: >=3.11
License-File: LICENSE
Requires-Dist: wxPython (>=4.2.0)
Requires-Dist: trio (>=0.22.0)
